{
  "legislative_session": "891",
  "identifier": "HB 243",
  "title": "Relating to the selection of the chief appraiser of an appraisal district; authorizing a fee.",
  "from_organization": "~{\"classification\": \"lower\"}",
  "classification": [
    "bill"
  ],
  "subject": [
    "Elections--General (I0310)",
    "RESIDENCY REQUIREMENTS (S0266)",
    "Taxation--Property-Appraisals & Appraisal Districts (I0792)"
  ],
  "abstracts": [],
  "other_titles": [],
  "other_identifiers": [
    {
      "identifier": "ocd-bill-tx-891-hb243"
    }
  ],
  "actions": [
    {
      "description": "Filed",
      "date": "2025-07-31",
      "organization_id": "~{\"classification\": \"lower\"}",
      "classification": [
        "filing"
      ],
      "related_entities": [],
      "_processing": {
        "log_file_created": "2026-07-13T06:03:53Z"
      }
    }
  ],
  "sponsorships": [
    {
      "name": "Bell, Cecil",
      "classification": "primary",
      "entity_type": "person",
      "primary": true,
      "person_id": "~{\"name\": \"Bell, Cecil\"}",
      "organization_id": null
    }
  ],
  "related_bills": [],
  "versions": [
    {
      "note": "Introduced",
      "links": [
        {
          "url": "http://capitol.texas.gov/tlodocs/891/billtext/html/HB00243I.HTM",
          "media_type": "text/html"
        },
        {
          "url": "http://capitol.texas.gov/tlodocs/891/billtext/pdf/HB00243I.PDF",
          "media_type": "application/pdf"
        }
      ],
      "date": "",
      "classification": ""
    }
  ],
  "documents": [],
  "citations": [],
  "sources": [
    {
      "url": "ftp://ftp.legis.state.tx.us/bills/891/billhistory/house_bills/HB00200_HB00299/HB 243.xml",
      "note": ""
    },
    {
      "url": "https://capitol.texas.gov/BillLookup/History.aspx?LegSess=891&Bill=HB243",
      "note": ""
    }
  ],
  "extras": {},
  "jurisdiction": {
    "id": "ocd-jurisdiction/country:us/state:tx/government",
    "name": "Texas",
    "classification": "state",
    "division_id": "ocd-division/country:us/state:tx"
  },
  "_processing": {
    "logs_latest_update": "2026-07-13T06:03:53Z",
    "text_extraction_latest_update": "2026-07-13T08:38:23.300338Z"
  }
}